{
    "command": "mdrun -o traj.trr -e ener.edr -s topol.tpr -g mdlog.log -cpo state.cpt -c outgro", 
    "command_idx": "mdrun -o traj.trr -e ener.edr -s topol.tpr -g mdlog.log -cpo state.cpt -c outgro", 
    "mode": "profiled", 
    "profile": {
        "cmd": "mdrun -o traj.trr -e ener.edr -s topol.tpr -g mdlog.log -cpo state.cpt -c outgro", 
        "cpu": {
            "branch_misses": 43790888.0, 
            "branch_misses_perc": -1.0, 
            "branches": 5178191619.0, 
            "branches_perc": -1.0, 
            "cores_per_socket": 2, 
            "cycles": 61267472198.0, 
            "cycles_idle_back": 27.77, 
            "cycles_idle_back_perc": 33.3, 
            "cycles_idle_front": 55.27, 
            "cycles_idle_front_perc": 41.66, 
            "cycles_perc": -1.0, 
            "cycles_stalled_back": 17014776205.0, 
            "cycles_stalled_back_perc": -1.0, 
            "cycles_stalled_front": 33864908300.0, 
            "cycles_stalled_front_perc": -1.0, 
            "efficiency": 0.27060068006859755, 
            "flops": 4068056859.8275084, 
            "flops_per_core": 10680000000, 
            "flops_per_cycle": 4, 
            "frequency": 2670000000.0, 
            "load": 0.86, 
            "num_sockets": 1, 
            "ops": 75503647193.0, 
            "ops_per_cycle": 1.23, 
            "ops_per_cycle_perc": -1.0, 
            "ops_perc": -1.0, 
            "real": 18.560125827789307, 
            "sequence": [
                [
                    0.500143728, 
                    {
                        "branch_misses": 1176250.0, 
                        "branch_misses_perc": 43.21, 
                        "branches": 139790125.0, 
                        "branches_perc": 43.99, 
                        "cycles": 1651211235.0, 
                        "cycles_perc": 40.79, 
                        "cycles_stalled_back": 465247383.0, 
                        "cycles_stalled_back_perc": 34.38, 
                        "cycles_stalled_front": 915965085.0, 
                        "cycles_stalled_front_perc": 41.6, 
                        "efficiency": 0.2679771521243637, 
                        "flops": 4043884895.0236163, 
                        "ops": 2022523667.0, 
                        "ops_perc": 43.18, 
                        "real": 0.500143728, 
                        "utilization": 0.3786409077737468
                    }
                ], 
                [
                    1.000360262, 
                    {
                        "branch_misses": 1211233.0, 
                        "branch_misses_perc": 40.75, 
                        "branches": 139761273.0, 
                        "branches_perc": 39.99, 
                        "cycles": 1653495882.0, 
                        "cycles_perc": 41.65, 
                        "cycles_stalled_back": 459072626.0, 
                        "cycles_stalled_back_perc": 31.98, 
                        "cycles_stalled_front": 914172555.0, 
                        "cycles_stalled_front_perc": 40.86, 
                        "efficiency": 0.2708202097380497, 
                        "flops": 4078462552.3793654, 
                        "ops": 2040114402.0, 
                        "ops_perc": 39.98, 
                        "real": 0.5002165340000001, 
                        "utilization": 0.38187851614039003
                    }
                ], 
                [
                    1.500484326, 
                    {
                        "branch_misses": 1191094.0, 
                        "branch_misses_perc": 41.68, 
                        "branches": 139921292.0, 
                        "branches_perc": 42.49, 
                        "cycles": 1655655257.0, 
                        "cycles_perc": 42.31, 
                        "cycles_stalled_back": 458120292.0, 
                        "cycles_stalled_back_perc": 35.18, 
                        "cycles_stalled_front": 914317723.0, 
                        "cycles_stalled_front_perc": 43.12, 
                        "efficiency": 0.27098738404246486, 
                        "flops": 4080270986.5206566, 
                        "ops": 2040641708.0, 
                        "ops_perc": 43.28, 
                        "real": 0.500124064, 
                        "utilization": 0.3820478451798368
                    }
                ], 
                [
                    2.000657947, 
                    {
                        "branch_misses": 1177374.0, 
                        "branch_misses_perc": 42.28, 
                        "branches": 140008475.0, 
                        "branches_perc": 41.5, 
                        "cycles": 1654979753.0, 
                        "cycles_perc": 40.11, 
                        "cycles_stalled_back": 459033980.0, 
                        "cycles_stalled_back_perc": 31.98, 
                        "cycles_stalled_front": 914416227.0, 
                        "cycles_stalled_front_perc": 39.99, 
                        "efficiency": 0.2709261931313479, 
                        "flops": 4081611133.186889, 
                        "ops": 2041514220.0, 
                        "ops_perc": 40.68, 
                        "real": 0.5001736210000001, 
                        "utilization": 0.3821733270774241
                    }
                ], 
                [
                    2.500787688, 
                    {
                        "branch_misses": 1200506.0, 
                        "branch_misses_perc": 40.15, 
                        "branches": 139854659.0, 
                        "branches_perc": 40.96, 
                        "cycles": 1652493527.0, 
                        "cycles_perc": 43.85, 
                        "cycles_stalled_back": 455922382.0, 
                        "cycles_stalled_back_perc": 33.74, 
                        "cycles_stalled_front": 913495785.0, 
                        "cycles_stalled_front_perc": 43.35, 
                        "efficiency": 0.27132687723712057, 
                        "flops": 4078246392.4695907, 
                        "ops": 2039652312.0, 
                        "ops_perc": 41.74, 
                        "real": 0.5001297409999999, 
                        "utilization": 0.38185827644846354
                    }
                ], 
                [
                    3.000971403, 
                    {
                        "branch_misses": 1183058.0, 
                        "branch_misses_perc": 43.82, 
                        "branches": 139464447.0, 
                        "branches_perc": 43.03, 
                        "cycles": 1653930775.0, 
                        "cycles_perc": 39.98, 
                        "cycles_stalled_back": 457239827.0, 
                        "cycles_stalled_back_perc": 33.42, 
                        "cycles_stalled_front": 913563118.0, 
                        "cycles_stalled_front_perc": 40.64, 
                        "efficiency": 0.2707308600888857, 
                        "flops": 4069634432.22057, 
                        "ops": 2035564869.0, 
                        "ops_perc": 42.22, 
                        "real": 0.5001837149999999, 
                        "utilization": 0.38105191312926684
                    }
                ], 
                [
                    3.501150924, 
                    {
                        "branch_misses": 1186205.0, 
                        "branch_misses_perc": 39.97, 
                        "branches": 139873611.0, 
                        "branches_perc": 39.98, 
                        "cycles": 1652888515.0, 
                        "cycles_perc": 42.62, 
                        "cycles_stalled_back": 458472332.0, 
                        "cycles_stalled_back_perc": 32.2, 
                        "cycles_stalled_front": 914716960.0, 
                        "cycles_stalled_front_perc": 41.83, 
                        "efficiency": 0.27062386761316287, 
                        "flops": 4074544281.4720902, 
                        "ops": 2038003607.0, 
                        "ops_perc": 40.2, 
                        "real": 0.5001795210000002, 
                        "utilization": 0.38151163684195605
                    }
                ], 
                [
                    4.001317361, 
                    {
                        "branch_misses": 1180439.0, 
                        "branch_misses_perc": 42.65, 
                        "branches": 139901978.0, 
                        "branches_perc": 43.46, 
                        "cycles": 1655460964.0, 
                        "cycles_perc": 41.35, 
                        "cycles_stalled_back": 459529106.0, 
                        "cycles_stalled_back_perc": 34.95, 
                        "cycles_stalled_front": 914609801.0, 
                        "cycles_stalled_front_perc": 42.16, 
                        "efficiency": 0.2707621601204044, 
                        "flops": 4080325939.5831885, 
                        "ops": 2040842087.0, 
                        "ops_perc": 43.75, 
                        "real": 0.5001664369999999, 
                        "utilization": 0.3820529905976768
                    }
                ], 
                [
                    4.501483819, 
                    {
                        "branch_misses": 1183586.0, 
                        "branch_misses_perc": 41.32, 
                        "branches": 140003053.0, 
                        "branches_perc": 40.54, 
                        "cycles": 1653480739.0, 
                        "cycles_perc": 41.09, 
                        "cycles_stalled_back": 453373614.0, 
                        "cycles_stalled_back_perc": 31.99, 
                        "cycles_stalled_front": 915501855.0, 
                        "cycles_stalled_front_perc": 40.3, 
                        "efficiency": 0.2716188496027717, 
                        "flops": 4082353189.3056307, 
                        "ops": 2041856135.0, 
                        "ops_perc": 39.99, 
                        "real": 0.5001664579999998, 
                        "utilization": 0.3822428079874186
                    }
                ], 
                [
                    5.001666851, 
                    {
                        "branch_misses": 1196026.0, 
                        "branch_misses_perc": 41.12, 
                        "branches": 139349007.0, 
                        "branches_perc": 41.93, 
                        "cycles": 1652419961.0, 
                        "cycles_perc": 42.88, 
                        "cycles_stalled_back": 460170915.0, 
                        "cycles_stalled_back_perc": 34.71, 
                        "cycles_stalled_front": 914058699.0, 
                        "cycles_stalled_front_perc": 43.69, 
                        "efficiency": 0.27009370887498546, 
                        "flops": 4066658476.731368, 
                        "ops": 2034073567.0, 
                        "ops_perc": 42.71, 
                        "real": 0.5001830320000007, 
                        "utilization": 0.3807732656115513
                    }
                ], 
                [
                    5.501845834, 
                    {
                        "branch_misses": 1169905.0, 
                        "branch_misses_perc": 42.85, 
                        "branches": 140072699.0, 
                        "branches_perc": 42.06, 
                        "cycles": 1654440263.0, 
                        "cycles_perc": 39.98, 
                        "cycles_stalled_back": 460822194.0, 
                        "cycles_stalled_back_perc": 32.45, 
                        "cycles_stalled_front": 914843599.0, 
                        "cycles_stalled_front_perc": 39.99, 
                        "efficiency": 0.2706272909460898, 
                        "flops": 4081967770.325131, 
                        "ops": 2041714488.0, 
                        "ops_perc": 41.25, 
                        "real": 0.5001789829999996, 
                        "utilization": 0.3822067200678962
                    }
                ], 
                [
                    6.002015396, 
                    {
                        "branch_misses": 1172359.0, 
                        "branch_misses_perc": 39.98, 
                        "branches": 139864313.0, 
                        "branches_perc": 40.4, 
                        "cycles": 1654884684.0, 
                        "cycles_perc": 43.58, 
                        "cycles_stalled_back": 460882618.0, 
                        "cycles_stalled_back_perc": 33.18, 
                        "cycles_stalled_front": 912728203.0, 
                        "cycles_stalled_front_perc": 42.8, 
                        "efficiency": 0.2706964758838725, 
                        "flops": 4077375654.0586934, 
                        "ops": 2039379195.0, 
                        "ops_perc": 41.19, 
                        "real": 0.500169562, 
                        "utilization": 0.3817767466347091
                    }
                ], 
                [
                    6.502179175, 
                    {
                        "branch_misses": 1182519.0, 
                        "branch_misses_perc": 43.61, 
                        "branches": 139869667.0, 
                        "branches_perc": 43.58, 
                        "cycles": 1654044270.0, 
                        "cycles_perc": 40.39, 
                        "cycles_stalled_back": 460586542.0, 
                        "cycles_stalled_back_perc": 33.98, 
                        "cycles_stalled_front": 914515475.0, 
                        "cycles_stalled_front_perc": 41.2, 
                        "efficiency": 0.27043257651849995, 
                        "flops": 4076394856.2536736, 
                        "ops": 2038865056.0, 
                        "ops_perc": 42.77, 
                        "real": 0.5001637790000002, 
                        "utilization": 0.3816849116342391
                    }
                ], 
                [
                    7.002358658, 
                    {
                        "branch_misses": 1183915.0, 
                        "branch_misses_perc": 40.34, 
                        "branches": 139797056.0, 
                        "branches_perc": 39.99, 
                        "cycles": 1653154017.0, 
                        "cycles_perc": 42.05, 
                        "cycles_stalled_back": 464538689.0, 
                        "cycles_stalled_back_perc": 31.98, 
                        "cycles_stalled_front": 914473024.0, 
                        "cycles_stalled_front_perc": 41.28, 
                        "efficiency": 0.26984248996220317, 
                        "flops": 4075640339.6898217, 
                        "ops": 2038551678.0, 
                        "ops_perc": 39.98, 
                        "real": 0.5001794830000001, 
                        "utilization": 0.38161426401590093
                    }
                ], 
                [
                    7.502537759, 
                    {
                        "branch_misses": 1185798.0, 
                        "branch_misses_perc": 42.09, 
                        "branches": 140019987.0, 
                        "branches_perc": 42.9, 
                        "cycles": 1654116247.0, 
                        "cycles_perc": 41.91, 
                        "cycles_stalled_back": 459548263.0, 
                        "cycles_stalled_back_perc": 35.18, 
                        "cycles_stalled_front": 914684862.0, 
                        "cycles_stalled_front_perc": 42.72, 
                        "efficiency": 0.270766921512657, 
                        "flops": 4080600790.635596, 
                        "ops": 2041031235.0, 
                        "ops_perc": 43.69, 
                        "real": 0.5001791009999996, 
                        "utilization": 0.38207872571494345
                    }
                ], 
                [
                    8.002705538, 
                    {
                        "branch_misses": 1166710.0, 
                        "branch_misses_perc": 41.87, 
                        "branches": 139820856.0, 
                        "branches_perc": 41.09, 
                        "cycles": 1651960554.0, 
                        "cycles_perc": 40.52, 
                        "cycles_stalled_back": 461472192.0, 
                        "cycles_stalled_back_perc": 31.98, 
                        "cycles_stalled_front": 912848443.0, 
                        "cycles_stalled_front_perc": 39.99, 
                        "efficiency": 0.2705501381427348, 
                        "flops": 4076473856.5856256, 
                        "ops": 2038920875.0, 
                        "ops_perc": 40.27, 
                        "real": 0.5001677790000008, 
                        "utilization": 0.38169230866906606
                    }
                ], 
                [
                    8.502828937, 
                    {
                        "branch_misses": 1171111.0, 
                        "branch_misses_perc": 40.56, 
                        "branches": 140090856.0, 
                        "branches_perc": 41.37, 
                        "cycles": 1654416086.0, 
                        "cycles_perc": 43.44, 
                        "cycles_stalled_back": 458609608.0, 
                        "cycles_stalled_back_perc": 34.14, 
                        "cycles_stalled_front": 913498017.0, 
                        "cycles_stalled_front_perc": 43.76, 
                        "efficiency": 0.27124371852578893, 
                        "flops": 4084589093.580886, 
                        "ops": 2042798581.0, 
                        "ops_perc": 42.15, 
                        "real": 0.5001233989999996, 
                        "utilization": 0.38245216232030765
                    }
                ], 
                [
                    9.002962933, 
                    {
                        "branch_misses": 1181790.0, 
                        "branch_misses_perc": 43.42, 
                        "branches": 139749320.0, 
                        "branches_perc": 42.63, 
                        "cycles": 1652332440.0, 
                        "cycles_perc": 39.99, 
                        "cycles_stalled_back": 460400766.0, 
                        "cycles_stalled_back_perc": 33.02, 
                        "cycles_stalled_front": 913025058.0, 
                        "cycles_stalled_front_perc": 40.23, 
                        "efficiency": 0.2705533458753894, 
                        "flops": 4074161089.4213333, 
                        "ops": 2037626466.0, 
                        "ops_perc": 41.82, 
                        "real": 0.5001339959999989, 
                        "utilization": 0.3814757574364544
                    }
                ], 
                [
                    9.50314595, 
                    {
                        "branch_misses": 1183234.0, 
                        "branch_misses_perc": 39.97, 
                        "branches": 140199101.0, 
                        "branches_perc": 39.98, 
                        "cycles": 1654341931.0, 
                        "cycles_perc": 43.02, 
                        "cycles_stalled_back": 458593314.0, 
                        "cycles_stalled_back_perc": 32.6, 
                        "cycles_stalled_front": 914003791.0, 
                        "cycles_stalled_front_perc": 42.23, 
                        "efficiency": 0.2712742426957559, 
                        "flops": 4086190103.4916487, 
                        "ops": 2043842894.0, 
                        "ops_perc": 40.6, 
                        "real": 0.5001830170000012, 
                        "utilization": 0.3826020696153229
                    }
                ], 
                [
                    10.003298119, 
                    {
                        "branch_misses": 1167034.0, 
                        "branch_misses_perc": 43.04, 
                        "branches": 140166244.0, 
                        "branches_perc": 43.85, 
                        "cycles": 1653199545.0, 
                        "cycles_perc": 40.95, 
                        "cycles_stalled_back": 460657902.0, 
                        "cycles_stalled_back_perc": 34.55, 
                        "cycles_stalled_front": 913090897.0, 
                        "cycles_stalled_front_perc": 41.76, 
                        "efficiency": 0.2709908495904026, 
                        "flops": 4084010100.534026, 
                        "ops": 2042626510.0, 
                        "ops_perc": 43.35, 
                        "real": 0.5001521689999997, 
                        "utilization": 0.38239794948820466
                    }
                ], 
                [
                    10.503418144, 
                    {
                        "branch_misses": 1166810.0, 
                        "branch_misses_perc": 40.93, 
                        "branches": 140065750.0, 
                        "branches_perc": 40.14, 
                        "cycles": 1654336163.0, 
                        "cycles_perc": 41.47, 
                        "cycles_stalled_back": 457745162.0, 
                        "cycles_stalled_back_perc": 31.99, 
                        "cycles_stalled_front": 913726357.0, 
                        "cycles_stalled_front_perc": 40.69, 
                        "efficiency": 0.27145439369695956, 
                        "flops": 4087075611.4994655, 
                        "ops": 2044028357.0, 
                        "ops_perc": 39.99, 
                        "real": 0.5001200249999993, 
                        "utilization": 0.3826849823501372
                    }
                ], 
                [
                    11.003604206, 
                    {
                        "branch_misses": 1188144.0, 
                        "branch_misses_perc": 41.49, 
                        "branches": 139659707.0, 
                        "branches_perc": 42.31, 
                        "cycles": 1650677981.0, 
                        "cycles_perc": 42.5, 
                        "cycles_stalled_back": 457853779.0, 
                        "cycles_stalled_back_perc": 35.09, 
                        "cycles_stalled_front": 911247454.0, 
                        "cycles_stalled_front_perc": 43.32, 
                        "efficiency": 0.2709176329179582, 
                        "flops": 4068409359.235596, 
                        "ops": 2034961656.0, 
                        "ops_perc": 43.09, 
                        "real": 0.5001860620000009, 
                        "utilization": 0.38093720592093594
                    }
                ], 
                [
                    11.503779259, 
                    {
                        "branch_misses": 1187802.0, 
                        "branch_misses_perc": 42.46, 
                        "branches": 139905292.0, 
                        "branches_perc": 41.67, 
                        "cycles": 1655296679.0, 
                        "cycles_perc": 39.98, 
                        "cycles_stalled_back": 458562241.0, 
                        "cycles_stalled_back_perc": 32.06, 
                        "cycles_stalled_front": 914128421.0, 
                        "cycles_stalled_front_perc": 39.99, 
                        "efficiency": 0.2712160275213742, 
                        "flops": 4085330359.3292203, 
                        "ops": 2043380329.0, 
                        "ops_perc": 40.86, 
                        "real": 0.5001750529999995, 
                        "utilization": 0.38252156922558245
                    }
                ], 
                [
                    12.003902508, 
                    {
                        "branch_misses": 1195221.0, 
                        "branch_misses_perc": 39.99, 
                        "branches": 140103930.0, 
                        "branches_perc": 40.78, 
                        "cycles": 1652713168.0, 
                        "cycles_perc": 43.97, 
                        "cycles_stalled_back": 462029422.0, 
                        "cycles_stalled_back_perc": 33.57, 
                        "cycles_stalled_front": 913174282.0, 
                        "cycles_stalled_front_perc": 43.18, 
                        "efficiency": 0.2707629687987977, 
                        "flops": 4083857069.4001102, 
                        "ops": 2042431866.0, 
                        "ops_perc": 41.57, 
                        "real": 0.5001232489999996, 
                        "utilization": 0.3823836207303474
                    }
                ], 
                [
                    12.504064591, 
                    {
                        "branch_misses": 1166712.0, 
                        "branch_misses_perc": 43.98, 
                        "branches": 139918073.0, 
                        "branches_perc": 43.21, 
                        "cycles": 1653983041.0, 
                        "cycles_perc": 40.01, 
                        "cycles_stalled_back": 457932167.0, 
                        "cycles_stalled_back_perc": 33.6, 
                        "cycles_stalled_front": 913250189.0, 
                        "cycles_stalled_front_perc": 40.82, 
                        "efficiency": 0.27121948756071385, 
                        "flops": 4081018678.499057, 
                        "ops": 2041170803.0, 
                        "ops_perc": 42.4, 
                        "real": 0.5001620830000011, 
                        "utilization": 0.3821178537920465
                    }
                ], 
                [
                    13.00419998, 
                    {
                        "branch_misses": 1186184.0, 
                        "branch_misses_perc": 39.99, 
                        "branches": 139761586.0, 
                        "branches_perc": 40.0, 
                        "cycles": 1650618235.0, 
                        "cycles_perc": 42.42, 
                        "cycles_stalled_back": 459831809.0, 
                        "cycles_stalled_back_perc": 32.01, 
                        "cycles_stalled_front": 912698974.0, 
                        "cycles_stalled_front_perc": 41.63, 
                        "efficiency": 0.2708649566817876, 
                        "flops": 4077926079.332102, 
                        "ops": 2039515146.0, 
                        "ops_perc": 40.02, 
                        "real": 0.5001353889999987, 
                        "utilization": 0.38182828458165746
                    }
                ], 
                [
                    13.50430314, 
                    {
                        "branch_misses": 1172352.0, 
                        "branch_misses_perc": 42.45, 
                        "branches": 139704633.0, 
                        "branches_perc": 43.26, 
                        "cycles": 1652388847.0, 
                        "cycles_perc": 41.55, 
                        "cycles_stalled_back": 458796287.0, 
                        "cycles_stalled_back_perc": 35.14, 
                        "cycles_stalled_front": 912772522.0, 
                        "cycles_stalled_front_perc": 42.36, 
                        "efficiency": 0.27072242352123366, 
                        "flops": 4072389994.4963346, 
                        "ops": 2036615105.0, 
                        "ops_perc": 43.95, 
                        "real": 0.5001031600000001, 
                        "utilization": 0.3813099245783085
                    }
                ], 
                [
                    14.004422931, 
                    {
                        "branch_misses": 1162423.0, 
                        "branch_misses_perc": 41.53, 
                        "branches": 139919701.0, 
                        "branches_perc": 40.74, 
                        "cycles": 1651028287.0, 
                        "cycles_perc": 40.87, 
                        "cycles_stalled_back": 459855584.0, 
                        "cycles_stalled_back_perc": 31.98, 
                        "cycles_stalled_front": 912159062.0, 
                        "cycles_stalled_front_perc": 40.08, 
                        "efficiency": 0.27092341845395773, 
                        "flops": 4077726522.1243663, 
                        "ops": 2039351736.0, 
                        "ops_perc": 39.99, 
                        "real": 0.5001197910000013, 
                        "utilization": 0.381809599449847
                    }
                ], 
                [
                    14.504588602, 
                    {
                        "branch_misses": 1161892.0, 
                        "branch_misses_perc": 40.9, 
                        "branches": 139693003.0, 
                        "branches_perc": 41.71, 
                        "cycles": 1653865764.0, 
                        "cycles_perc": 43.09, 
                        "cycles_stalled_back": 455163793.0, 
                        "cycles_stalled_back_perc": 34.5, 
                        "cycles_stalled_front": 913547844.0, 
                        "cycles_stalled_front_perc": 43.91, 
                        "efficiency": 0.27101525879636995, 
                        "flops": 4069428065.565903, 
                        "ops": 2035388219.0, 
                        "ops_perc": 42.5, 
                        "real": 0.5001656709999995, 
                        "utilization": 0.38103259040879245
                    }
                ], 
                [
                    15.004723206, 
                    {
                        "branch_misses": 1169820.0, 
                        "branch_misses_perc": 43.07, 
                        "branches": 139876422.0, 
                        "branches_perc": 42.28, 
                        "cycles": 1651998692.0, 
                        "cycles_perc": 39.98, 
                        "cycles_stalled_back": 458340496.0, 
                        "cycles_stalled_back_perc": 32.66, 
                        "cycles_stalled_front": 914324545.0, 
                        "cycles_stalled_front_perc": 40.01, 
                        "efficiency": 0.27103630486725316, 
                        "flops": 4081870559.7903447, 
                        "ops": 2041484716.0, 
                        "ops_perc": 41.47, 
                        "real": 0.5001346039999994, 
                        "utilization": 0.3821976179578975
                    }
                ], 
                [
                    15.504902795, 
                    {
                        "branch_misses": 1181931.0, 
                        "branch_misses_perc": 39.97, 
                        "branches": 140051806.0, 
                        "branches_perc": 40.17, 
                        "cycles": 1653304439.0, 
                        "cycles_perc": 43.37, 
                        "cycles_stalled_back": 459503143.0, 
                        "cycles_stalled_back_perc": 32.95, 
                        "cycles_stalled_front": 914220084.0, 
                        "cycles_stalled_front_perc": 42.58, 
                        "efficiency": 0.27091801859394177, 
                        "flops": 4082204835.8314753, 
                        "ops": 2041835537.0, 
                        "ops_perc": 40.95, 
                        "real": 0.500179589, 
                        "utilization": 0.382228917212685
                    }
                ], 
                [
                    16.005066115, 
                    {
                        "branch_misses": 1165665.0, 
                        "branch_misses_perc": 43.4, 
                        "branches": 140218674.0, 
                        "branches_perc": 43.81, 
                        "cycles": 1653703346.0, 
                        "cycles_perc": 40.6, 
                        "cycles_stalled_back": 457419768.0, 
                        "cycles_stalled_back_perc": 34.2, 
                        "cycles_stalled_front": 912971252.0, 
                        "cycles_stalled_front_perc": 41.41, 
                        "efficiency": 0.2716426149588141, 
                        "flops": 4087389555.075712, 
                        "ops": 2044362330.0, 
                        "ops_perc": 43.0, 
                        "real": 0.5001633200000022, 
                        "utilization": 0.3827143778160779
                    }
                ], 
                [
                    16.505231971, 
                    {
                        "branch_misses": 1159897.0, 
                        "branch_misses_perc": 40.57, 
                        "branches": 140115159.0, 
                        "branches_perc": 40.0, 
                        "cycles": 1654338240.0, 
                        "cycles_perc": 41.83, 
                        "cycles_stalled_back": 455829858.0, 
                        "cycles_stalled_back_perc": 31.98, 
                        "cycles_stalled_front": 913793957.0, 
                        "cycles_stalled_front_perc": 41.04, 
                        "efficiency": 0.2715575906813786, 
                        "flops": 4083325246.016003, 
                        "ops": 2042339867.0, 
                        "ops_perc": 39.99, 
                        "real": 0.5001658559999989, 
                        "utilization": 0.38233382453333364
                    }
                ], 
                [
                    17.00542419, 
                    {
                        "branch_misses": 1177361.0, 
                        "branch_misses_perc": 41.86, 
                        "branches": 139763046.0, 
                        "branches_perc": 42.68, 
                        "cycles": 1622372072.0, 
                        "cycles_perc": 42.94, 
                        "cycles_stalled_back": 460830660.0, 
                        "cycles_stalled_back_perc": 35.18, 
                        "cycles_stalled_front": 904179560.0, 
                        "cycles_stalled_front_perc": 43.42, 
                        "efficiency": 0.27203688514448787, 
                        "flops": 4079222379.9067235, 
                        "ops": 2040395294.0, 
                        "ops_perc": 43.46, 
                        "real": 0.5001922189999988, 
                        "utilization": 0.38194966103995537
                    }
                ], 
                [
                    17.505604427, 
                    {
                        "branch_misses": 1151227.0, 
                        "branch_misses_perc": 42.09, 
                        "branches": 139874504.0, 
                        "branches_perc": 41.31, 
                        "cycles": 1685607016.0, 
                        "cycles_perc": 39.56, 
                        "cycles_stalled_back": 458373033.0, 
                        "cycles_stalled_back_perc": 31.98, 
                        "cycles_stalled_front": 922659759.0, 
                        "cycles_stalled_front_perc": 39.56, 
                        "efficiency": 0.2696697731943833, 
                        "flops": 4078030302.1048617, 
                        "ops": 2039750163.0, 
                        "ops_perc": 40.5, 
                        "real": 0.5001802370000021, 
                        "utilization": 0.3818380432682455
                    }
                ], 
                [
                    18.005773924, 
                    {
                        "branch_misses": 1163057.0, 
                        "branch_misses_perc": 40.34, 
                        "branches": 139985002.0, 
                        "branches_perc": 41.15, 
                        "cycles": 1652408065.0, 
                        "cycles_perc": 43.66, 
                        "cycles_stalled_back": 458688277.0, 
                        "cycles_stalled_back_perc": 33.94, 
                        "cycles_stalled_front": 912963797.0, 
                        "cycles_stalled_front_perc": 43.55, 
                        "efficiency": 0.27105504848686346, 
                        "flops": 4078960702.7955317, 
                        "ops": 2040171723.0, 
                        "ops_perc": 41.94, 
                        "real": 0.5001694969999981, 
                        "utilization": 0.3819251594377839
                    }
                ], 
                [
                    18.505939129, 
                    {
                        "branch_misses": 1168517.0, 
                        "branch_misses_perc": 43.62, 
                        "branches": 139689692.0, 
                        "branches_perc": 42.83, 
                        "cycles": 1652553499.0, 
                        "cycles_perc": 39.99, 
                        "cycles_stalled_back": 454012967.0, 
                        "cycles_stalled_back_perc": 33.23, 
                        "cycles_stalled_front": 911726570.0, 
                        "cycles_stalled_front_perc": 40.44, 
                        "efficiency": 0.2716133750718538, 
                        "flops": 4072898499.60673, 
                        "ops": 2037122113.0, 
                        "ops_perc": 42.02, 
                        "real": 0.5001652050000018, 
                        "utilization": 0.38135753741636047
                    }
                ], 
                [
                    19.006121705, 
                    {
                        "branch_misses": 122537.0, 
                        "branch_misses_perc": 31.55, 
                        "branches": 8605562.0, 
                        "branches_perc": 42.06, 
                        "cycles": 86056361.0, 
                        "cycles_perc": 76.74, 
                        "cycles_stalled_back": 33472081.0, 
                        "cycles_stalled_back_perc": 49.08, 
                        "cycles_stalled_front": 55176090.0, 
                        "cycles_stalled_front_perc": 66.54, 
                        "efficiency": 0.2718996194726403, 
                        "flops": 264739383.88449568, 
                        "ops": 132418027.0, 
                        "ops_perc": 52.56, 
                        "real": 0.5001825760000003, 
                        "utilization": 0.02478833182439098
                    }
                ]
            ], 
            "threads_per_core": 2, 
            "utilization": 0.3809042003583809
        }, 
        "mem": {
            "peak": 57643008.0, 
            "rss": 5799936.0, 
            "sequence": [
                [
                    0.17796683311462402, 
                    {
                        "rss": 2301952.0, 
                        "size": 56799232.0
                    }
                ], 
                [
                    0.6789028644561768, 
                    {
                        "rss": 3497984.0, 
                        "size": 843776.0
                    }
                ], 
                [
                    1.1796538829803467, 
                    {
                        "rss": 0.0, 
                        "size": 0.0
                    }
                ], 
                [
                    1.6804118156433105, 
                    {
                        "rss": 0.0, 
                        "size": 0.0
                    }
                ], 
                [
                    2.181126832962036, 
                    {
                        "rss": 0.0, 
                        "size": 0.0
                    }
                ], 
                [
                    2.6818408966064453, 
                    {
                        "rss": 0.0, 
                        "size": 0.0
                    }
                ], 
                [
                    3.182583808898926, 
                    {
                        "rss": 0.0, 
                        "size": 0.0
                    }
                ], 
                [
                    3.6833338737487793, 
                    {
                        "rss": 0.0, 
                        "size": 0.0
                    }
                ], 
                [
                    4.184053897857666, 
                    {
                        "rss": 0.0, 
                        "size": 0.0
                    }
                ], 
                [
                    4.684774875640869, 
                    {
                        "rss": 0.0, 
                        "size": 0.0
                    }
                ], 
                [
                    5.185495853424072, 
                    {
                        "rss": 0.0, 
                        "size": 0.0
                    }
                ], 
                [
                    5.6862499713897705, 
                    {
                        "rss": 0.0, 
                        "size": 0.0
                    }
                ], 
                [
                    6.186976909637451, 
                    {
                        "rss": 0.0, 
                        "size": 0.0
                    }
                ], 
                [
                    6.687698841094971, 
                    {
                        "rss": 0.0, 
                        "size": 0.0
                    }
                ], 
                [
                    7.188421010971069, 
                    {
                        "rss": 0.0, 
                        "size": 0.0
                    }
                ], 
                [
                    7.689177989959717, 
                    {
                        "rss": 0.0, 
                        "size": 0.0
                    }
                ], 
                [
                    8.189910888671875, 
                    {
                        "rss": 0.0, 
                        "size": 0.0
                    }
                ], 
                [
                    8.690626859664917, 
                    {
                        "rss": 0.0, 
                        "size": 0.0
                    }
                ], 
                [
                    9.191350936889648, 
                    {
                        "rss": 0.0, 
                        "size": 0.0
                    }
                ], 
                [
                    9.692110776901245, 
                    {
                        "rss": 0.0, 
                        "size": 0.0
                    }
                ], 
                [
                    10.192832946777344, 
                    {
                        "rss": 0.0, 
                        "size": 0.0
                    }
                ], 
                [
                    10.693549871444702, 
                    {
                        "rss": 0.0, 
                        "size": 0.0
                    }
                ], 
                [
                    11.194278955459595, 
                    {
                        "rss": 0.0, 
                        "size": 0.0
                    }
                ], 
                [
                    11.695035934448242, 
                    {
                        "rss": 0.0, 
                        "size": 0.0
                    }
                ], 
                [
                    12.195755004882812, 
                    {
                        "rss": 0.0, 
                        "size": 0.0
                    }
                ], 
                [
                    12.696472883224487, 
                    {
                        "rss": 0.0, 
                        "size": 0.0
                    }
                ], 
                [
                    13.197194814682007, 
                    {
                        "rss": 0.0, 
                        "size": 0.0
                    }
                ], 
                [
                    13.697954893112183, 
                    {
                        "rss": 0.0, 
                        "size": 0.0
                    }
                ], 
                [
                    14.198678970336914, 
                    {
                        "rss": 0.0, 
                        "size": 0.0
                    }
                ], 
                [
                    14.699395895004272, 
                    {
                        "rss": 0.0, 
                        "size": 0.0
                    }
                ], 
                [
                    15.200121879577637, 
                    {
                        "rss": 0.0, 
                        "size": 0.0
                    }
                ], 
                [
                    15.700877904891968, 
                    {
                        "rss": 0.0, 
                        "size": 0.0
                    }
                ], 
                [
                    16.201596975326538, 
                    {
                        "rss": 0.0, 
                        "size": 0.0
                    }
                ], 
                [
                    16.702324867248535, 
                    {
                        "rss": 0.0, 
                        "size": 0.0
                    }
                ], 
                [
                    17.203046798706055, 
                    {
                        "rss": 0.0, 
                        "size": 0.0
                    }
                ], 
                [
                    17.703924894332886, 
                    {
                        "rss": 0.0, 
                        "size": 0.0
                    }
                ], 
                [
                    18.20465588569641, 
                    {
                        "rss": 0.0, 
                        "size": 0.0
                    }
                ], 
                [
                    18.705381870269775, 
                    {
                        "rss": 0.0, 
                        "size": 0.0
                    }
                ]
            ], 
            "size": 57643008.0
        }, 
        "sto": {
            "read": 25320.0, 
            "sequence": [
                [
                    0.1762387752532959, 
                    {
                        "read": 11940.0, 
                        "write": 0.0
                    }
                ], 
                [
                    0.6775507926940918, 
                    {
                        "read": 13380.0, 
                        "write": 23965.0
                    }
                ], 
                [
                    1.1782808303833008, 
                    {
                        "read": 0.0, 
                        "write": 10368.0
                    }
                ], 
                [
                    1.6785109043121338, 
                    {
                        "read": 0.0, 
                        "write": 10368.0
                    }
                ], 
                [
                    2.1791319847106934, 
                    {
                        "read": 0.0, 
                        "write": 10368.0
                    }
                ], 
                [
                    2.679766893386841, 
                    {
                        "read": 0.0, 
                        "write": 10368.0
                    }
                ], 
                [
                    3.1804208755493164, 
                    {
                        "read": 0.0, 
                        "write": 10368.0
                    }
                ], 
                [
                    3.68117094039917, 
                    {
                        "read": 0.0, 
                        "write": 10368.0
                    }
                ], 
                [
                    4.181295871734619, 
                    {
                        "read": 0.0, 
                        "write": 10368.0
                    }
                ], 
                [
                    4.681861877441406, 
                    {
                        "read": 0.0, 
                        "write": 10368.0
                    }
                ], 
                [
                    5.182245969772339, 
                    {
                        "read": 0.0, 
                        "write": 10368.0
                    }
                ], 
                [
                    5.6829798221588135, 
                    {
                        "read": 0.0, 
                        "write": 10368.0
                    }
                ], 
                [
                    6.183167934417725, 
                    {
                        "read": 0.0, 
                        "write": 10368.0
                    }
                ], 
                [
                    6.6838698387146, 
                    {
                        "read": 0.0, 
                        "write": 10368.0
                    }
                ], 
                [
                    7.184487819671631, 
                    {
                        "read": 0.0, 
                        "write": 10368.0
                    }
                ], 
                [
                    7.68523383140564, 
                    {
                        "read": 0.0, 
                        "write": 10368.0
                    }
                ], 
                [
                    8.185887813568115, 
                    {
                        "read": 0.0, 
                        "write": 10368.0
                    }
                ], 
                [
                    8.686540842056274, 
                    {
                        "read": 0.0, 
                        "write": 10368.0
                    }
                ], 
                [
                    9.187155961990356, 
                    {
                        "read": 0.0, 
                        "write": 10368.0
                    }
                ], 
                [
                    9.687711000442505, 
                    {
                        "read": 0.0, 
                        "write": 10368.0
                    }
                ], 
                [
                    10.188357830047607, 
                    {
                        "read": 0.0, 
                        "write": 10368.0
                    }
                ], 
                [
                    10.68900990486145, 
                    {
                        "read": 0.0, 
                        "write": 10368.0
                    }
                ], 
                [
                    11.189669847488403, 
                    {
                        "read": 0.0, 
                        "write": 10368.0
                    }
                ], 
                [
                    11.690418004989624, 
                    {
                        "read": 0.0, 
                        "write": 10368.0
                    }
                ], 
                [
                    12.191082000732422, 
                    {
                        "read": 0.0, 
                        "write": 10368.0
                    }
                ], 
                [
                    12.691734790802002, 
                    {
                        "read": 0.0, 
                        "write": 10368.0
                    }
                ], 
                [
                    13.19239592552185, 
                    {
                        "read": 0.0, 
                        "write": 10368.0
                    }
                ], 
                [
                    13.693147897720337, 
                    {
                        "read": 0.0, 
                        "write": 10368.0
                    }
                ], 
                [
                    14.193803787231445, 
                    {
                        "read": 0.0, 
                        "write": 10368.0
                    }
                ], 
                [
                    14.694454908370972, 
                    {
                        "read": 0.0, 
                        "write": 10368.0
                    }
                ], 
                [
                    15.195113897323608, 
                    {
                        "read": 0.0, 
                        "write": 10368.0
                    }
                ], 
                [
                    15.695841789245605, 
                    {
                        "read": 0.0, 
                        "write": 10368.0
                    }
                ], 
                [
                    16.196496963500977, 
                    {
                        "read": 0.0, 
                        "write": 10368.0
                    }
                ], 
                [
                    16.697107791900635, 
                    {
                        "read": 0.0, 
                        "write": 10368.0
                    }
                ], 
                [
                    17.197771787643433, 
                    {
                        "read": 0.0, 
                        "write": 10368.0
                    }
                ], 
                [
                    17.698521852493286, 
                    {
                        "read": 0.0, 
                        "write": 10368.0
                    }
                ], 
                [
                    18.19919180870056, 
                    {
                        "read": 0.0, 
                        "write": 10368.0
                    }
                ], 
                [
                    18.699853897094727, 
                    {
                        "read": 0.0, 
                        "write": 10368.0
                    }
                ]
            ], 
            "write": 397213.0
        }, 
        "sys": {
            "hostname": "thinkie"
        }, 
        "time": {
            "real": 18.560125827789307, 
            "start": 1431741997.996251
        }
    }, 
    "tags": {
        "prob": "1", 
        "rate": "2", 
        "step": "1000000"
    }, 
    "type": "synapse_profile"
}
