{
    "command": "mdrun -o traj.trr -e ener.edr -s topol.tpr -g mdlog.log -cpo state.cpt -c outgro", 
    "command_idx": "mdrun -o traj.trr -e ener.edr -s topol.tpr -g mdlog.log -cpo state.cpt -c outgro", 
    "mode": "emulated", 
    "profile": {
        "cmd": "mdrun -o traj.trr -e ener.edr -s topol.tpr -g mdlog.log -cpo state.cpt -c outgro", 
        "cpu": {
            "branch_misses": 192679.0, 
            "branch_misses_perc": -1.0, 
            "branches": 634083228.0, 
            "branches_perc": -1.0, 
            "cores_per_socket": 2, 
            "cycles": 8642272744.0, 
            "cycles_idle_back": 56.72, 
            "cycles_idle_back_perc": 34.3, 
            "cycles_idle_front": 62.26, 
            "cycles_idle_front_perc": 34.76, 
            "cycles_perc": -1.0, 
            "cycles_stalled_back": 4901581379.0, 
            "cycles_stalled_back_perc": -1.0, 
            "cycles_stalled_front": 5380499305.0, 
            "cycles_stalled_front_perc": -1.0, 
            "efficiency": 0.16400482757007293, 
            "flops": 2685821551.5923357, 
            "flops_per_core": 10680000000, 
            "flops_per_cycle": 4, 
            "frequency": 2670000000.0, 
            "load": 0.56, 
            "num_sockets": 1, 
            "ops": 8068519653.0, 
            "ops_per_cycle": 0.93, 
            "ops_per_cycle_perc": -1.0, 
            "ops_perc": -1.0, 
            "real": 3.0041160583496094, 
            "sequence": [
                [
                    0.200302734, 
                    {
                        "branch_misses": 3719.0, 
                        "branch_misses_perc": 42.62, 
                        "branches": 5577166.0, 
                        "branches_perc": 42.64, 
                        "cycles": 275220910.0, 
                        "cycles_perc": 33.61, 
                        "cycles_stalled_back": 179250592.0, 
                        "cycles_stalled_back_perc": 33.21, 
                        "cycles_stalled_front": 212879391.0, 
                        "cycles_stalled_front_perc": 33.71, 
                        "efficiency": 0.01156038695477896, 
                        "flops": 91585220.19974026, 
                        "ops": 18344770.0, 
                        "ops_perc": 42.68, 
                        "real": 0.200302734, 
                        "utilization": 0.008575395149788414
                    }
                ], 
                [
                    0.400650787, 
                    {
                        "branch_misses": 4602.0, 
                        "branch_misses_perc": 41.35, 
                        "branches": 34696725.0, 
                        "branches_perc": 43.15, 
                        "cycles": 616407342.0, 
                        "cycles_perc": 34.46, 
                        "cycles_stalled_back": 319204225.0, 
                        "cycles_stalled_back_perc": 38.91, 
                        "cycles_stalled_front": 429572428.0, 
                        "cycles_stalled_front_perc": 36.0, 
                        "efficiency": 0.1071362355789182, 
                        "flops": 1793817861.5591538, 
                        "ops": 359387916.0, 
                        "ops_perc": 46.8, 
                        "real": 0.200348053, 
                        "utilization": 0.1679604739287597
                    }
                ], 
                [
                    0.600887106, 
                    {
                        "branch_misses": 2450.0, 
                        "branch_misses_perc": 40.16, 
                        "branches": 62643326.0, 
                        "branches_perc": 40.2, 
                        "cycles": 651796996.0, 
                        "cycles_perc": 34.96, 
                        "cycles_stalled_back": 355244577.0, 
                        "cycles_stalled_back_perc": 33.29, 
                        "cycles_stalled_front": 324890519.0, 
                        "cycles_stalled_front_perc": 36.37, 
                        "efficiency": 0.23379856660380663, 
                        "flops": 4145827311.1782494, 
                        "ops": 830145200.0, 
                        "ops_perc": 40.15, 
                        "real": 0.20023631899999994, 
                        "utilization": 0.3881860778256788
                    }
                ], 
                [
                    0.801187737, 
                    {
                        "branch_misses": 14490.0, 
                        "branch_misses_perc": 33.91, 
                        "branches": 42719075.0, 
                        "branches_perc": 37.05, 
                        "cycles": 521039901.0, 
                        "cycles_perc": 32.35, 
                        "cycles_stalled_back": 430958368.0, 
                        "cycles_stalled_back_perc": 36.42, 
                        "cycles_stalled_front": 370020146.0, 
                        "cycles_stalled_front_perc": 39.03, 
                        "efficiency": 0.13898802533050375, 
                        "flops": 2582062399.9931374, 
                        "ops": 517188728.0, 
                        "ops_perc": 43.61, 
                        "real": 0.20030063100000006, 
                        "utilization": 0.24176614232145482
                    }
                ], 
                [
                    1.001479115, 
                    {
                        "branch_misses": 8950.0, 
                        "branch_misses_perc": 46.5, 
                        "branches": 55998189.0, 
                        "branches_perc": 41.87, 
                        "cycles": 691079906.0, 
                        "cycles_perc": 32.91, 
                        "cycles_stalled_back": 208985152.0, 
                        "cycles_stalled_back_perc": 34.81, 
                        "cycles_stalled_front": 346400694.0, 
                        "cycles_stalled_front_perc": 31.28, 
                        "efficiency": 0.26155550492237656, 
                        "flops": 3928606692.196207, 
                        "ops": 786866048.0, 
                        "ops_perc": 40.24, 
                        "real": 0.20029137799999996, 
                        "utilization": 0.3678470685576973
                    }
                ], 
                [
                    1.201784976, 
                    {
                        "branch_misses": 28745.0, 
                        "branch_misses_perc": 42.1, 
                        "branches": 31143296.0, 
                        "branches_perc": 42.49, 
                        "cycles": 539480284.0, 
                        "cycles_perc": 33.29, 
                        "cycles_stalled_back": 387723019.0, 
                        "cycles_stalled_back_perc": 32.84, 
                        "cycles_stalled_front": 335085043.0, 
                        "cycles_stalled_front_perc": 38.2, 
                        "efficiency": 0.13152081191142231, 
                        "flops": 2185870292.6321273, 
                        "ops": 437842631.0, 
                        "ops_perc": 41.26, 
                        "real": 0.20030586099999992, 
                        "utilization": 0.20466950305544263
                    }
                ], 
                [
                    1.402082563, 
                    {
                        "branch_misses": 12214.0, 
                        "branch_misses_perc": 44.24, 
                        "branches": 46699344.0, 
                        "branches_perc": 40.15, 
                        "cycles": 648825718.0, 
                        "cycles_perc": 37.48, 
                        "cycles_stalled_back": 469908143.0, 
                        "cycles_stalled_back_perc": 32.02, 
                        "cycles_stalled_front": 546229716.0, 
                        "cycles_stalled_front_perc": 30.32, 
                        "efficiency": 0.11610045295434825, 
                        "flops": 2665433852.6804104, 
                        "ops": 533879969.0, 
                        "ops_perc": 40.17, 
                        "real": 0.2002975870000001, 
                        "utilization": 0.2495724581161433
                    }
                ], 
                [
                    1.6022923, 
                    {
                        "branch_misses": 7303.0, 
                        "branch_misses_perc": 40.55, 
                        "branches": 55341657.0, 
                        "branches_perc": 45.83, 
                        "cycles": 645158464.0, 
                        "cycles_perc": 27.99, 
                        "cycles_stalled_back": 418499363.0, 
                        "cycles_stalled_back_perc": 31.9, 
                        "cycles_stalled_front": 299594133.0, 
                        "cycles_stalled_front_perc": 36.08, 
                        "efficiency": 0.22054520175513231, 
                        "flops": 4059405802.0265017, 
                        "ops": 812732568.0, 
                        "ops_perc": 43.35, 
                        "real": 0.200209737, 
                        "utilization": 0.38009417621970987
                    }
                ], 
                [
                    1.802501172, 
                    {
                        "branch_misses": 17671.0, 
                        "branch_misses_perc": 44.02, 
                        "branches": 37460893.0, 
                        "branches_perc": 42.02, 
                        "cycles": 643493531.0, 
                        "cycles_perc": 34.86, 
                        "cycles_stalled_back": 467484855.0, 
                        "cycles_stalled_back_perc": 31.76, 
                        "cycles_stalled_front": 492111955.0, 
                        "cycles_stalled_front_perc": 32.31, 
                        "efficiency": 0.10276913918791325, 
                        "flops": 2195957769.5438, 
                        "ops": 439650228.0, 
                        "ops_perc": 40.59, 
                        "real": 0.20020887199999993, 
                        "utilization": 0.20561402336552434
                    }
                ], 
                [
                    2.002772243, 
                    {
                        "branch_misses": 4422.0, 
                        "branch_misses_perc": 39.49, 
                        "branches": 32943356.0, 
                        "branches_perc": 45.07, 
                        "cycles": 586138314.0, 
                        "cycles_perc": 33.64, 
                        "cycles_stalled_back": 314640675.0, 
                        "cycles_stalled_back_perc": 36.18, 
                        "cycles_stalled_front": 348026510.0, 
                        "cycles_stalled_front_perc": 38.59, 
                        "efficiency": 0.14769017748203975, 
                        "flops": 2293460976.1986046, 
                        "ops": 459313886.0, 
                        "ops_perc": 41.87, 
                        "real": 0.20027107099999997, 
                        "utilization": 0.2147435370972476
                    }
                ], 
                [
                    2.203085979, 
                    {
                        "branch_misses": 2588.0, 
                        "branch_misses_perc": 39.72, 
                        "branches": 61878223.0, 
                        "branches_perc": 44.49, 
                        "cycles": 676821444.0, 
                        "cycles_perc": 30.67, 
                        "cycles_stalled_back": 222421740.0, 
                        "cycles_stalled_back_perc": 35.81, 
                        "cycles_stalled_front": 354238083.0, 
                        "cycles_stalled_front_perc": 28.75, 
                        "efficiency": 0.23184121600779697, 
                        "flops": 3475430431.790259, 
                        "ops": 696176454.0, 
                        "ops_perc": 51.2, 
                        "real": 0.20031373600000002, 
                        "utilization": 0.32541483443729013
                    }
                ], 
                [
                    2.403386205, 
                    {
                        "branch_misses": 11568.0, 
                        "branch_misses_perc": 37.21, 
                        "branches": 12053565.0, 
                        "branches_perc": 33.93, 
                        "cycles": 570152244.0, 
                        "cycles_perc": 36.93, 
                        "cycles_stalled_back": 309276034.0, 
                        "cycles_stalled_back_perc": 37.85, 
                        "cycles_stalled_front": 435295996.0, 
                        "cycles_stalled_front_perc": 40.46, 
                        "efficiency": 0.030665621877803598, 
                        "flops": 470395794.76061106, 
                        "ops": 94220384.0, 
                        "ops_perc": 38.86, 
                        "real": 0.20030022599999997, 
                        "utilization": 0.04404455007121827
                    }
                ], 
                [
                    2.603627755, 
                    {
                        "branch_misses": 4817.0, 
                        "branch_misses_perc": 47.19, 
                        "branches": 51001589.0, 
                        "branches_perc": 49.28, 
                        "cycles": 640923427.0, 
                        "cycles_perc": 31.66, 
                        "cycles_stalled_back": 170381821.0, 
                        "cycles_stalled_back_perc": 32.8, 
                        "cycles_stalled_front": 312807884.0, 
                        "cycles_stalled_front_perc": 25.06, 
                        "efficiency": 0.2728865449112795, 
                        "flops": 3622458400.866348, 
                        "ops": 725366685.0, 
                        "ops_perc": 43.53, 
                        "real": 0.20024155000000032, 
                        "utilization": 0.33918149820845955
                    }
                ], 
                [
                    2.803896797, 
                    {
                        "branch_misses": 7454.0, 
                        "branch_misses_perc": 40.82, 
                        "branches": 59661007.0, 
                        "branches_perc": 40.79, 
                        "cycles": 653151621.0, 
                        "cycles_perc": 35.39, 
                        "cycles_stalled_back": 243886283.0, 
                        "cycles_stalled_back_perc": 32.02, 
                        "cycles_stalled_front": 344441186.0, 
                        "cycles_stalled_front_perc": 35.44, 
                        "efficiency": 0.261626659875748, 
                        "flops": 4163621919.15813, 
                        "ops": 833844573.0, 
                        "ops_perc": 40.82, 
                        "real": 0.20026904199999995, 
                        "utilization": 0.3898522396215478
                    }
                ], 
                [
                    3.0040939, 
                    {
                        "branch_misses": 24971.0, 
                        "branch_misses_perc": 40.88, 
                        "branches": 32574546.0, 
                        "branches_perc": 44.51, 
                        "cycles": 504195008.0, 
                        "cycles_perc": 30.69, 
                        "cycles_stalled_back": 249404776.0, 
                        "cycles_stalled_back_perc": 39.05, 
                        "cycles_stalled_front": 264359382.0, 
                        "cycles_stalled_front_perc": 39.72, 
                        "efficiency": 0.1591377102129454, 
                        "flops": 1942737997.562334, 
                        "ops": 388930519.0, 
                        "ops_perc": 46.61, 
                        "real": 0.20019710299999982, 
                        "utilization": 0.181904306887859
                    }
                ]
            ], 
            "threads_per_core": 2, 
            "utilization": 0.25148141868842094
        }, 
        "mem": {
            "peak": 745013248.0, 
            "rss": 16670720.0, 
            "sequence": [
                [
                    0.005405902862548828, 
                    {
                        "rss": 12255232.0, 
                        "size": 65290240.0
                    }
                ], 
                [
                    0.20608997344970703, 
                    {
                        "rss": 385024.0, 
                        "size": 377716736.0
                    }
                ], 
                [
                    0.4066169261932373, 
                    {
                        "rss": 4030464.0, 
                        "size": 226504704.0
                    }
                ], 
                [
                    0.6071200370788574, 
                    {
                        "rss": 0.0, 
                        "size": 75501568.0
                    }
                ], 
                [
                    0.8073549270629883, 
                    {
                        "rss": 0.0, 
                        "size": 0.0
                    }
                ], 
                [
                    1.0081448554992676, 
                    {
                        "rss": 0.0, 
                        "size": 0.0
                    }
                ], 
                [
                    1.2086520195007324, 
                    {
                        "rss": 0.0, 
                        "size": 0.0
                    }
                ], 
                [
                    1.4091880321502686, 
                    {
                        "rss": 0.0, 
                        "size": 0.0
                    }
                ], 
                [
                    1.6099369525909424, 
                    {
                        "rss": 0.0, 
                        "size": 0.0
                    }
                ], 
                [
                    1.81050705909729, 
                    {
                        "rss": 0.0, 
                        "size": 0.0
                    }
                ], 
                [
                    2.0110390186309814, 
                    {
                        "rss": 0.0, 
                        "size": 0.0
                    }
                ], 
                [
                    2.2115979194641113, 
                    {
                        "rss": 0.0, 
                        "size": 0.0
                    }
                ], 
                [
                    2.412142038345337, 
                    {
                        "rss": 0.0, 
                        "size": 0.0
                    }
                ], 
                [
                    2.612658977508545, 
                    {
                        "rss": 0.0, 
                        "size": 0.0
                    }
                ], 
                [
                    2.8133130073547363, 
                    {
                        "rss": 0.0, 
                        "size": 0.0
                    }
                ]
            ], 
            "size": 745013248.0
        }, 
        "sto": {
            "read": 83639.0, 
            "sequence": [
                [
                    0.003473997116088867, 
                    {
                        "read": 4745.0, 
                        "write": 0.0
                    }
                ], 
                [
                    0.2055978775024414, 
                    {
                        "read": 59444.0, 
                        "write": 663.0
                    }
                ], 
                [
                    0.4063689708709717, 
                    {
                        "read": 18562.0, 
                        "write": 18559.0
                    }
                ], 
                [
                    0.6068708896636963, 
                    {
                        "read": 55.0, 
                        "write": 43.0
                    }
                ], 
                [
                    0.8073790073394775, 
                    {
                        "read": 72.0, 
                        "write": 4168.0
                    }
                ], 
                [
                    1.0078959465026855, 
                    {
                        "read": 35.0, 
                        "write": 39.0
                    }
                ], 
                [
                    1.208409070968628, 
                    {
                        "read": 131.0, 
                        "write": 5247.0
                    }
                ], 
                [
                    1.4089269638061523, 
                    {
                        "read": 88.0, 
                        "write": 5216.0
                    }
                ], 
                [
                    1.609454870223999, 
                    {
                        "read": 43.0, 
                        "write": 35.0
                    }
                ], 
                [
                    1.809931993484497, 
                    {
                        "read": 103.0, 
                        "write": 5231.0
                    }
                ], 
                [
                    2.0104260444641113, 
                    {
                        "read": 115.0, 
                        "write": 5227.0
                    }
                ], 
                [
                    2.210955858230591, 
                    {
                        "read": 0.0, 
                        "write": 8.0
                    }
                ], 
                [
                    2.4114630222320557, 
                    {
                        "read": 211.0, 
                        "write": 9419.0
                    }
                ], 
                [
                    2.6119229793548584, 
                    {
                        "read": 12.0, 
                        "write": 12.0
                    }
                ], 
                [
                    2.812398910522461, 
                    {
                        "read": 23.0, 
                        "write": 39.0
                    }
                ]
            ], 
            "write": 53906.0
        }, 
        "sys": {
            "hostname": "thinkie"
        }, 
        "time": {
            "real": 3.0041160583496094, 
            "start": 1431890718.393841
        }
    }, 
    "tags": {
        "prob": "1", 
        "rate": "5", 
        "step": "100000"
    }, 
    "type": "synapse_profile"
}
