{
    "command": "mdrun -o traj.trr -e ener.edr -s topol.tpr -g mdlog.log -cpo state.cpt -c outgro", 
    "command_idx": "mdrun -o traj.trr -e ener.edr -s topol.tpr -g mdlog.log -cpo state.cpt -c outgro", 
    "mode": "emulated", 
    "profile": {
        "cmd": "mdrun -o traj.trr -e ener.edr -s topol.tpr -g mdlog.log -cpo state.cpt -c outgro", 
        "cpu": {
            "branch_misses": 915487.0, 
            "branch_misses_perc": -1.0, 
            "branches": 28450407621.0, 
            "branches_perc": -1.0, 
            "cores_per_socket": 2, 
            "cycles": 293148913984.0, 
            "cycles_idle_back": 48.84, 
            "cycles_idle_back_perc": 33.32, 
            "cycles_idle_front": 51.8, 
            "cycles_idle_front_perc": 41.65, 
            "cycles_perc": -1.0, 
            "cycles_stalled_back": 143183027505.0, 
            "cycles_stalled_back_perc": -1.0, 
            "cycles_stalled_front": 151865421172.0, 
            "cycles_stalled_front_perc": -1.0, 
            "efficiency": 0.2518115658982096, 
            "flops": 4437877582.611231, 
            "flops_per_core": 10680000000, 
            "flops_per_cycle": 4, 
            "frequency": 2670000000.0, 
            "load": 1.2, 
            "num_sockets": 1, 
            "ops": 397208021353.0, 
            "ops_per_cycle": 1.35, 
            "ops_per_cycle_perc": -1.0, 
            "ops_perc": -1.0, 
            "real": 89.50405097007751, 
            "sequence": [
                [
                    10.00021453, 
                    {
                        "branch_misses": 96922.0, 
                        "branch_misses_perc": 41.71, 
                        "branches": 3078060953.0, 
                        "branches_perc": 41.84, 
                        "cycles": 32457731614.0, 
                        "cycles_perc": 41.72, 
                        "cycles_stalled_back": 12773060994.0, 
                        "cycles_stalled_back_perc": 33.52, 
                        "cycles_stalled_front": 17072408469.0, 
                        "cycles_stalled_front_perc": 41.73, 
                        "efficiency": 0.2640363399003248, 
                        "flops": 4282885090.4661546, 
                        "ops": 42829769712.0, 
                        "ops_perc": 41.84, 
                        "real": 10.00021453, 
                        "utilization": 0.401019203227168
                    }
                ], 
                [
                    20.000527132, 
                    {
                        "branch_misses": 109040.0, 
                        "branch_misses_perc": 41.62, 
                        "branches": 3186754791.0, 
                        "branches_perc": 41.65, 
                        "cycles": 32920037563.0, 
                        "cycles_perc": 41.74, 
                        "cycles_stalled_back": 18799212067.0, 
                        "cycles_stalled_back_perc": 33.36, 
                        "cycles_stalled_front": 17018049479.0, 
                        "cycles_stalled_front_perc": 41.7, 
                        "efficiency": 0.23710477509313227, 
                        "flops": 4452605285.168265, 
                        "ops": 44527444745.0, 
                        "ops_perc": 41.69, 
                        "real": 10.000312602, 
                        "utilization": 0.416910607225493
                    }
                ], 
                [
                    30.000826584, 
                    {
                        "branch_misses": 94067.0, 
                        "branch_misses_perc": 41.62, 
                        "branches": 3210407034.0, 
                        "branches_perc": 41.61, 
                        "cycles": 32864940657.0, 
                        "cycles_perc": 41.67, 
                        "cycles_stalled_back": 17598507050.0, 
                        "cycles_stalled_back_perc": 33.3, 
                        "cycles_stalled_front": 16880623535.0, 
                        "cycles_stalled_front_perc": 41.63, 
                        "efficiency": 0.24557428685367189, 
                        "flops": 4489207731.47664, 
                        "ops": 44893421617.0, 
                        "ops_perc": 41.6, 
                        "real": 10.000299452, 
                        "utilization": 0.420337802572719
                    }
                ], 
                [
                    40.001105616, 
                    {
                        "branch_misses": 99709.0, 
                        "branch_misses_perc": 41.68, 
                        "branches": 3187128824.0, 
                        "branches_perc": 41.76, 
                        "cycles": 32907535542.0, 
                        "cycles_perc": 41.64, 
                        "cycles_stalled_back": 13591531761.0, 
                        "cycles_stalled_back_perc": 33.33, 
                        "cycles_stalled_front": 17001394952.0, 
                        "cycles_stalled_front_perc": 41.67, 
                        "efficiency": 0.2666897936072585, 
                        "flops": 4450282343.781706, 
                        "ops": 44504065209.0, 
                        "ops_perc": 41.66, 
                        "real": 10.000279031999998, 
                        "utilization": 0.416693103350347
                    }
                ], 
                [
                    50.001366962, 
                    {
                        "branch_misses": 92716.0, 
                        "branch_misses_perc": 41.78, 
                        "branches": 3190143459.0, 
                        "branches_perc": 41.73, 
                        "cycles": 32913458605.0, 
                        "cycles_perc": 41.64, 
                        "cycles_stalled_back": 16879850071.0, 
                        "cycles_stalled_back_perc": 33.39, 
                        "cycles_stalled_front": 16976745963.0, 
                        "cycles_stalled_front_perc": 41.66, 
                        "efficiency": 0.24762272804482505, 
                        "flops": 4457042436.978725, 
                        "ops": 44571589200.0, 
                        "ops_perc": 41.72, 
                        "real": 10.000261346000002, 
                        "utilization": 0.4173260708781578
                    }
                ], 
                [
                    60.001617326, 
                    {
                        "branch_misses": 110227.0, 
                        "branch_misses_perc": 41.52, 
                        "branches": 3188086639.0, 
                        "branches_perc": 41.66, 
                        "cycles": 32872830431.0, 
                        "cycles_perc": 41.74, 
                        "cycles_stalled_back": 14243420790.0, 
                        "cycles_stalled_back_perc": 33.4, 
                        "cycles_stalled_front": 16986932819.0, 
                        "cycles_stalled_front_perc": 41.72, 
                        "efficiency": 0.26272710259846666, 
                        "flops": 4451461555.52791, 
                        "ops": 44515730041.0, 
                        "ops_perc": 41.75, 
                        "real": 10.000250364000003, 
                        "utilization": 0.41680351643519753
                    }
                ], 
                [
                    70.001895059, 
                    {
                        "branch_misses": 118137.0, 
                        "branch_misses_perc": 41.73, 
                        "branches": 3177725030.0, 
                        "branches_perc": 41.69, 
                        "cycles": 32895155653.0, 
                        "cycles_perc": 41.73, 
                        "cycles_stalled_back": 18435366689.0, 
                        "cycles_stalled_back_perc": 33.35, 
                        "cycles_stalled_front": 17029612523.0, 
                        "cycles_stalled_front_perc": 41.73, 
                        "efficiency": 0.2383545130905375, 
                        "flops": 4439337318.652846, 
                        "ops": 44394606137.0, 
                        "ops_perc": 41.68, 
                        "real": 10.000277733000004, 
                        "utilization": 0.4156682882633751
                    }
                ], 
                [
                    80.002122216, 
                    {
                        "branch_misses": 98523.0, 
                        "branch_misses_perc": 41.63, 
                        "branches": 3178055843.0, 
                        "branches_perc": 41.8, 
                        "cycles": 32880515928.0, 
                        "cycles_perc": 41.7, 
                        "cycles_stalled_back": 15786290588.0, 
                        "cycles_stalled_back_perc": 33.42, 
                        "cycles_stalled_front": 17012953023.0, 
                        "cycles_stalled_front_perc": 41.72, 
                        "efficiency": 0.2525082984120086, 
                        "flops": 4431831442.046513, 
                        "ops": 44319321142.0, 
                        "ops_perc": 41.85, 
                        "real": 10.000227156999998, 
                        "utilization": 0.4149654908283252
                    }
                ], 
                [
                    90.002358352, 
                    {
                        "branch_misses": 120753.0, 
                        "branch_misses_perc": 41.76, 
                        "branches": 3024336089.0, 
                        "branches_perc": 41.69, 
                        "cycles": 31088816109.0, 
                        "cycles_perc": 41.72, 
                        "cycles_stalled_back": 14743033929.0, 
                        "cycles_stalled_back_perc": 33.44, 
                        "cycles_stalled_front": 16055558853.0, 
                        "cycles_stalled_front_perc": 41.74, 
                        "efficiency": 0.2556421742277864, 
                        "flops": 4230886293.6434174, 
                        "ops": 42309862001.0, 
                        "ops_perc": 41.66, 
                        "real": 10.000236135999998, 
                        "utilization": 0.3961504020265372
                    }
                ]
            ], 
            "threads_per_core": 2, 
            "utilization": 0.4155316088587295
        }, 
        "mem": {
            "peak": 745005056.0, 
            "rss": 16642048.0, 
            "sequence": [
                [
                    0.008844852447509766, 
                    {
                        "rss": 12316672.0, 
                        "size": 65282048.0
                    }
                ], 
                [
                    10.01970386505127, 
                    {
                        "rss": 4325376.0, 
                        "size": 679723008.0
                    }
                ], 
                [
                    20.030043840408325, 
                    {
                        "rss": 0.0, 
                        "size": 0.0
                    }
                ], 
                [
                    30.039493799209595, 
                    {
                        "rss": 0.0, 
                        "size": 0.0
                    }
                ], 
                [
                    40.04678988456726, 
                    {
                        "rss": 0.0, 
                        "size": 0.0
                    }
                ], 
                [
                    50.05723690986633, 
                    {
                        "rss": 0.0, 
                        "size": 0.0
                    }
                ], 
                [
                    60.06739783287048, 
                    {
                        "rss": 0.0, 
                        "size": 0.0
                    }
                ], 
                [
                    70.07349991798401, 
                    {
                        "rss": 0.0, 
                        "size": 0.0
                    }
                ], 
                [
                    80.08408880233765, 
                    {
                        "rss": 0.0, 
                        "size": 0.0
                    }
                ]
            ], 
            "size": 745005056.0
        }, 
        "sto": {
            "read": 281376.0, 
            "sequence": [
                [
                    0.004488945007324219, 
                    {
                        "read": 5577.0, 
                        "write": 0.0
                    }
                ], 
                [
                    10.008760929107666, 
                    {
                        "read": 274936.0, 
                        "write": 419732.0
                    }
                ], 
                [
                    20.01515483856201, 
                    {
                        "read": 134.0, 
                        "write": 202886.0
                    }
                ], 
                [
                    30.024589776992798, 
                    {
                        "read": 47.0, 
                        "write": 39.0
                    }
                ], 
                [
                    40.02502799034119, 
                    {
                        "read": 142.0, 
                        "write": 201949.0
                    }
                ], 
                [
                    50.02929377555847, 
                    {
                        "read": 213.0, 
                        "write": 202886.0
                    }
                ], 
                [
                    60.03479599952698, 
                    {
                        "read": 142.0, 
                        "write": 202894.0
                    }
                ], 
                [
                    70.04509377479553, 
                    {
                        "read": 55.0, 
                        "write": 202878.0
                    }
                ], 
                [
                    80.05108785629272, 
                    {
                        "read": 130.0, 
                        "write": 202819.0
                    }
                ]
            ], 
            "write": 1636083.0
        }, 
        "sys": {
            "hostname": "thinkie"
        }, 
        "time": {
            "real": 89.50405097007751, 
            "start": 1431894428.138322
        }
    }, 
    "tags": {
        "prob": "1", 
        "rate": "0.1", 
        "step": "5000000"
    }, 
    "type": "synapse_profile"
}
